nr5103e_sdk/__init__.py
nr5103e_sdk/client.py
nr5103e_sdk/py.typed
nr5103e_sdk-1.0.0.dist-info/METADATA
nr5103e_sdk-1.0.0.dist-info/WHEEL
nr5103e_sdk-1.0.0.dist-info/RECORD
