Metadata-Version: 2.4
Name: nr5103e-sdk
Version: 1.0.0
Summary: SDK for interacting with the Zyxel NR5103E router.
Author-email: Gary Fernie <g@ryfernie.me>
Requires-Python: >=3.13
Requires-Dist: aiohttp>=3.9.0
